loss_watch/__init__.py
loss_watch/color.py
loss_watch/display_components.py
loss_watch/loss_progress_bar.py
loss_watch/style.py
loss_watch/util.py
loss_watch-0.2.dist-info/LICENSE
loss_watch-0.2.dist-info/METADATA
loss_watch-0.2.dist-info/WHEEL
loss_watch-0.2.dist-info/top_level.txt
loss_watch-0.2.dist-info/RECORD
