Metadata-Version: 2.1
Name: loss-watch
Version: 0.2
Summary: A dynamic progress indicator that displays train and validation losses.
Author-email: Fredrik Konrad <loss-watch@librico.mozmail.com>
License: MIT
Requires-Python: >=3.12
License-File: LICENSE
Requires-Dist: ipywidgets >=8.1
Provides-Extra: palettes
Requires-Dist: seaborn >=0.13 ; extra == 'palettes'
